glee/__init__.py
glee/agent_session.py
glee/claude_session.py
glee/cli.py
glee/config.py
glee/dispatch.py
glee/helpers.py
glee/logging.py
glee/mcp_server.py
glee/session_summary.py
glee/subagent.py
glee/types.py
glee/warmup.py
glee/agents/__init__.py
glee/agents/base.py
glee/agents/claude.py
glee/agents/codex.py
glee/agents/gemini.py
glee/agents/prompts.py
glee/cli/__init__.py
glee/cli/code_review.py
glee/cli/config.py
glee/cli/connect.py
glee/cli/logs.py
glee/cli/memory.py
glee/cli/theme.py
glee/connect/__init__.py
glee/connect/codex.py
glee/connect/connection.py
glee/connect/copilot.py
glee/connect/credential.py
glee/connect/storage.py
glee/db/__init__.py
glee/db/duckdb.py
glee/db/schema.py
glee/db/sqlite.py
glee/github/__init__.py
glee/github/auth.py
glee/github/client.py
glee/github/diff.py
glee/memory/__init__.py
glee/memory/capture.py
glee/memory/store.py
glee/schemas/__init__.py
glee/schemas/tool.schema.json
glee/tools/__init__.py
glee/tools/lint.py
glee/utils/__init__.py
glee-0.3.30.dist-info/METADATA
glee-0.3.30.dist-info/WHEEL
glee-0.3.30.dist-info/entry_points.txt
glee-0.3.30.dist-info/RECORD
