Metadata-Version: 2.4
Name: glee
Version: 0.3.30
Summary: The Conductor for Your AI Orchestra
Requires-Python: >=3.11
Requires-Dist: anthropic>=0.40.0
Requires-Dist: boto3>=1.35.0
Requires-Dist: duckdb>=1.2.0
Requires-Dist: fastembed>=0.7.4
Requires-Dist: google-cloud-aiplatform>=1.60.0
Requires-Dist: jsonschema>=4.26.0
Requires-Dist: lancedb>=0.26.1
Requires-Dist: langgraph>=1.0.5
Requires-Dist: loguru>=0.7.0
Requires-Dist: mcp>=1.0.0
Requires-Dist: openai>=1.0.0
Requires-Dist: openrouter>=0.1.0
Requires-Dist: pydantic>=2.12.5
Requires-Dist: pyyaml>=6.0.0
Requires-Dist: rich>=14.0.0
Requires-Dist: typer>=0.15.0
Provides-Extra: dev
Requires-Dist: pytest-asyncio>=0.24.0; extra == 'dev'
Requires-Dist: pytest>=8.0.0; extra == 'dev'
